cotyper/__init__.py
cotyper/compose/__init__.py
cotyper/compose/decompile.py
cotyper/compose/default_factory.py
cotyper/compose/fold.py
cotyper/log/__init__.py
cotyper/methods/__init__.py
cotyper/methods/doc.py
cotyper/methods/parse.py
cotyper/parser/__init__.py
cotyper/parser/app.py
cotyper/type_system/__init__.py
cotyper/type_system/custom_click_types.py
cotyper/type_system/extract_types.py
cotyper/type_system/type_checking.py
cotyper/utils/__init__.py
cotyper/utils/base_model.py
cotyper/utils/dictionary.py
cotyper/utils/file_io.py
cotyper/utils/string.py
cotyper/utils/tp.py
cotyper-0.8.0.dist-info/METADATA
cotyper-0.8.0.dist-info/WHEEL
cotyper-0.8.0.dist-info/licenses/LICENSE
cotyper-0.8.0.dist-info/RECORD
