Metadata-Version: 2.4
Name: cotyper
Version: 0.8.0
Summary: Wrapper around Typer to create command line interfaces for Pydantic models
Project-URL: Homepage, https://gitlab.opencode.de/lgln/cotyper
Author-email: Lukas Sanner <lukas.sanner@lgln.niedersachsen.de>
License: MIT
License-File: LICENSE
Classifier: License :: OSI Approved :: MIT License
Classifier: Operating System :: OS Independent
Classifier: Programming Language :: Python :: 3
Requires-Python: >=3.10
Requires-Dist: click==8.0.0
Requires-Dist: docstring-parser>=0.16
Requires-Dist: pydantic-core==2.33.2
Requires-Dist: pydantic>=2.11.5
Requires-Dist: typer>=0.15.2
Requires-Dist: typing-extensions>=4.12.2
Provides-Extra: build
Requires-Dist: build>=1.2.2.post1; extra == 'build'
Requires-Dist: hatchling>=1.27.0; extra == 'build'
Requires-Dist: twine>=6.1.0; extra == 'build'
Provides-Extra: dev
Requires-Dist: pre-commit>=4.2.0; extra == 'dev'
Requires-Dist: pytest>=8.4.1; extra == 'dev'
Requires-Dist: ruff>=0.12.4; extra == 'dev'
Requires-Dist: ty>=0.0.1a14; extra == 'dev'
Provides-Extra: test
Requires-Dist: pytest-cov>=6.1.1; extra == 'test'
Requires-Dist: pytest>=8.0; extra == 'test'
